pre-sim/trapezoid.v
module trapezoid (clk, reset, nt, xi, yi, busy, po, xo, yo);
	input clk, reset, nt;
	input [7:0] xi, yi;
	output po;
	output reg busy;
	output [7:0] xo, yo;
  
	parameter S0_RST = 0, S1_WAIT = 1, S2_START = 2, S3_RX_ENDPOINT = 3, S4_PREPARE_CAL = 4, S5_CAL = 5, S6_TX_RESULT = 6;
	
	reg [2:0] curr_state, next_state;
	reg count_flag;
	reg [31:0] end_point_x, end_point_y;
	reg [2:0]cnt;
	wire finish;
	
	Trapezoid_Rendering t1(finish, po, xo, yo, clk, count_flag, end_point_x, end_point_y);
	
	always@(posedge clk or posedge reset)begin
		if(reset)begin
			curr_state = S0_RST;
		end else begin
			curr_state = next_state;
		end
	end
	
	always@(curr_state or reset or nt or cnt or finish)begin
		case(curr_state)
		S0_RST:
			begin
				if(reset) next_state = S0_RST;
				else next_state = S1_WAIT;
			end
		S1_WAIT:
			begin
				next_state = S2_START;
			end
		S2_START:
			begin
				if(nt) next_state = S3_RX_ENDPOINT;
				else next_state = S2_START;
			end
		S3_RX_ENDPOINT:
			begin
				if(cnt == 3'd3) next_state = S4_PREPARE_CAL;
				else next_state = S3_RX_ENDPOINT;
			end
		S4_PREPARE_CAL:
			begin
				next_state = S5_CAL;
			end
		S5_CAL:
			begin
				if(finish) next_state = S1_WAIT;
				else next_state = S5_CAL;
			end
		S6_TX_RESULT:
			begin
			
			end
		default:;
		endcase
	end
	
  
  always@(curr_state)begin
		case(curr_state)
		S0_RST:
			begin
				busy = 1'd1;
				count_flag = 1'd0;
			end
		
		S1_WAIT:
			begin
				busy = 1'd0;
				count_flag = 1'd0;
			end
		
		S2_START:
			begin
				busy = 1'd0;
				count_flag = 1'd0;
			end
		
		S3_RX_ENDPOINT:
			begin
				busy = 1'd0;
				count_flag = 1'd0;
			end
		S4_PREPARE_CAL:
			begin
				busy = 1'd1;
				count_flag = 1'd0;
			end
		S5_CAL:
			begin
				busy = 1'd1;
				count_flag = 1'd1;
			end
		S6_TX_RESULT:
			begin
			
			end
		default:;
		endcase
	end
	
	
	always@(posedge clk)begin
		if(curr_state == S2_START) cnt = 3'd0;
		else if(curr_state == S3_RX_ENDPOINT) begin
			cnt = cnt + 3'd1;
			end_point_x[7:0] = xi;
			end_point_x  = end_point_x << 8;
			end_point_y[7:0] = yi;
			end_point_y = end_point_y << 8;
		end else if(curr_state == S4_PREPARE_CAL)begin
			end_point_x[7:0] = xi;
			end_point_y[7:0] = yi;
			

		end else cnt = 3'd0;
	end
	

endmodule

module Trapezoid_Rendering(finish, po, xo, yo, clk, count_flag, point_x, point_y);

	output reg po, finish;
	output reg [7:0]xo, yo;
	input clk, count_flag;
	input [31:0] point_x, point_y;

	reg signed[17:0] dxl, dxr;
	reg [17:0] xl, xr;
	reg [7:0] end_x;
	
	reg [2:0] curr_state, next_state;
	reg [7:0] i, j;
	reg init_slope, init_end_x, outdata, plus_slope, init_i;
	parameter S0_RST = 0, S1_PAR_INIT = 1, S2_OUTER_LOOP = 2, S3_END_X_INIT = 3, S4_OUTPUT = 4, S5_INCRESE_SLOPE = 5, S6_FINISH = 6;
	
	always@(posedge clk or posedge count_flag)begin
		if(count_flag) curr_state = next_state;
		else curr_state = S0_RST;
	end
	
	
	always@(curr_state or j or i)begin
		case(curr_state)
			S0_RST:
				begin
					next_state = S1_PAR_INIT;
				end
			S1_PAR_INIT:
				begin
					next_state = S2_OUTER_LOOP;
				end
			S2_OUTER_LOOP:
				begin
					next_state = S3_END_X_INIT;
				end
			S3_END_X_INIT:
				begin
					next_state = S4_OUTPUT; 
				end
			S4_OUTPUT:
				begin
					if(j >= end_x) next_state = S5_INCRESE_SLOPE;
					else next_state = S4_OUTPUT;
				end
			S5_INCRESE_SLOPE:
				begin
					if(i[6:0] <= point_y[30:24]) next_state = S3_END_X_INIT;
					else next_state = S6_FINISH;
				end
			S6_FINISH:
				begin
				
				end
			default:;
		endcase
	end
	
	always@(curr_state)begin
		case(curr_state)
			S0_RST:
				begin
					init_slope = 0;
					init_i = 0;
					init_end_x = 0;
					outdata = 0;
					plus_slope = 0;
					finish = 0;
				end
			S1_PAR_INIT:
				begin
					init_i = 0;
					init_end_x = 0;
					outdata = 0;
					plus_slope = 0;
					init_slope = 1;
					finish = 0;
				end
			S2_OUTER_LOOP:
				begin
					init_slope = 0;
					init_end_x = 0;
					outdata = 0;
					plus_slope = 0;
					init_i = 1;
					finish = 0;
				end
			S3_END_X_INIT:
				begin
					init_slope = 0;
					init_i = 0;
					outdata = 0;
					plus_slope = 0;
					init_end_x = 1;
					finish = 0;
				end
			S4_OUTPUT:
				begin
					init_slope = 0;
					init_i = 0;
					init_end_x = 0;
					plus_slope = 0;
					outdata = 1;
					finish = 0;
				end
			S5_INCRESE_SLOPE:
				begin
					init_slope = 0;
					init_i = 0;
					init_end_x = 0;
					outdata = 0;
					plus_slope = 1;
					finish = 0;
				end
			S6_FINISH:
				begin
					init_slope = 0;
					init_i = 0;
					init_end_x = 0;
					outdata = 0;
					plus_slope = 0;
					finish = 1;
				end
			default:;
		endcase
	end
	
	
	reg signed[17:0]tmp_x, tmp_y;
	always@(posedge init_slope or posedge plus_slope)begin
		if(init_slope)begin
			tmp_x = (point_x[31:24] - point_x[15:8]) << 10;
			tmp_y = (point_y[31:24] - point_y[15:8]);
	
			dxl = tmp_x / tmp_y;
			
			tmp_x = (point_x[23:16] - point_x[7:0]) << 10;
			tmp_y = (point_y[31:24] - point_y[15:8]);
			
			dxr = tmp_x / tmp_y;
				
			xl = point_x[15:8] << 10;
			xr = point_x[7:0] << 10;
		end else if(plus_slope)begin
			xl = xl + dxl;
			xr = xr + dxr;	
		end else begin
			dxl = dxl; 
			dxr = dxr;
			xl = xl;
			xr = xr;
		end
	end
	
	always@(posedge init_i or posedge plus_slope)begin
		if(init_i)begin
			i = point_y[15:8];
		end else if(plus_slope) i = i + 1;
		else i = 0;
	end

//need to consider the sign number	
	always@(posedge init_end_x)begin
		if(init_end_x)begin
			if(xl[9:0] == 10'd0) end_x = xr[17:10];  //xl is integer
			else if(xr[9:0] == 10'd0) end_x = xr[17:10] + 8'd1; //xr is not integer
			else begin
				//if(xr[9:0] != 10'd0) end_x = xr[17:10] + 8'd1;
				//else end_x = xr[17:10];
				end_x = xr[17:10];
			end
		end
	end
	
	always@(posedge clk)begin
		//if(next_state == S5_INCRESE_SLOPE) po = 0;
		if(outdata) po = 1;
		else po = 0;
	end
	
	always@(posedge clk or posedge init_end_x)begin
		if(init_end_x) begin
			if(i == (point_y[31:24] - point_y[15:8]) / 2) j = xl[17:10] + 1;
			else if(i == point_y[31:24]) j = xl[17:10] + 1;
			else j = xl[17:10];
		end
		else if(outdata)begin
			xo = j;
			yo = i;
			j = j + 1;
		end else begin
			xo = xo;
			yo = yo;
			j = j;
		end
	end
	
endmodule

pre-sim/testfixture.v
`timescale 1ns/10ps
`define CYCLE  100      // Modify your clock period here
`define INFILE1 "IN.DAT"  
`define INFILE2 "EXPECT.DAT"  

module test;
parameter INPUT_DATA = `INFILE1;
parameter EXPECT_DATA = `INFILE2;
reg     clk;
reg     reset;
reg     nt;
reg     [7:0] xi, yi;

wire    [7:0] xo, yo;
wire    po;
wire    busy;


integer i, j, k, l, m,  out_f, err, pattern_num, total_num, total_cycle_num;
integer a, b, c, d;
reg [15:0]  data_base [0:304128];
reg [15:0]  data_base_expect [0:304128];
reg [15:0]  data_tmp_expect;
reg [15:0]  data_tmp_i, data_tmp_i1, data_tmp_i2, data_tmp_i3;


trapezoid top(clk, reset, nt, xi, yi, busy, po, xo, yo);

//initial $sdf_annotate("chip.sdf",top);

initial	$readmemh( INPUT_DATA,  data_base);
initial	$readmemh( EXPECT_DATA,  data_base_expect);

initial begin
$dumpvars();
$dumpfile("trapezoid.vcd");
    clk   = 1'b1;
    reset = 1'b0;
    nt    = 1'b0;
    xi    = 8'bz;
    yi    = 8'bz;
   l = 0;
   i = 0;
   j = 0;
   k = 0;
   err = 0;
   pattern_num = 1 ; 
   total_num = 0 ;
end

initial begin

   out_f = $fopen("OUT.DAT");
   if (out_f == 0) begin
        $display("Output file open error !");
        $finish;
   end
end

always begin #(`CYCLE/2)  clk = ~clk;
end


initial begin 
   @(negedge clk)  
   reset = 1'b1;
   $display ("\n******START to VERIFY the Trapezoid Rendering Enginen OPERATION  ******\n");
   #(`CYCLE -0.1)
          reset = 1'b0;
   
    for  (i = 0; i < 68; i = i + k) begin
    if(busy ==1'b1) begin
      @(negedge clk)
           nt =1'b0;
           k  =0;
    end
    else begin   // else begin
           k  = 4;
      @(negedge clk)
           nt =1'b1;
      
      #(`CYCLE*0.3)  data_tmp_i = data_base[i] ;
           xi = data_tmp_i[15:8];
           yi = data_tmp_i[7:0];
      @(posedge clk)
      #(`CYCLE*0.2) 
           xi = 8'bz; 
           yi = 8'bz; 
      @(negedge clk)
           nt = 1'b0;
      #(`CYCLE*0.3)  data_tmp_i1 = data_base[i+1] ;
           xi = data_tmp_i1[15:8];
           yi = data_tmp_i1[7:0];
      @(posedge clk)
      #(`CYCLE*0.2) 
           xi = 8'bz; 
           yi = 8'bz; 
      @(negedge clk)
      #(`CYCLE*0.3)  data_tmp_i2 = data_base[i+2] ;
           xi = data_tmp_i2[15:8];
           yi = data_tmp_i2[7:0];
      @(posedge clk)
      #(`CYCLE*0.2) 
           xi = 8'bz; 
           yi = 8'bz; 

      @(negedge clk)
      #(`CYCLE*0.3)  data_tmp_i3 = data_base[i+3] ;
           xi = data_tmp_i3[15:8];
           yi = data_tmp_i3[7:0];
      @(posedge clk)
      #(`CYCLE*0.2) 
           xi = 8'bz; 
           yi = 8'bz; 
      
  $display("Waiting for the rendering operation of the trapezoid points with:"); 
    $display("(xul, yu)=(%h, %h)",data_tmp_i[15:8], data_tmp_i[7:0]); 
    $display("(xur, yu)=(%h, %h)",data_tmp_i1[15:8], data_tmp_i1[7:0]); 
    $display("(xdl, yd)=(%h, %h)",data_tmp_i2[15:8], data_tmp_i2[7:0]); 
    $display("(xdr, yd)=(%h, %h)",data_tmp_i3[15:8], data_tmp_i3[7:0]); 
  end //else end 
 end //for end
end 

always @ ( posedge clk) begin
  if (po ==1'b1) begin 
     data_tmp_expect = data_base_expect[l]; 
     if ((xo !== data_tmp_expect[15:8])|| (yo!== data_tmp_expect[7:0])) begin
         $display("ERROR at %d:xo=(%h) yo=(%h)!=expect xo=(%h), yo=(%h)",l 
         ,xo, yo, data_tmp_expect[15:8], data_tmp_expect[7:0]);
          err = err + 1 ;   
         end
       $fdisplay(out_f,"%h%h",xo,yo); 
        l = l + 1;
     end
    //if( l == 162 ) begin
    if( l == 119527 ) begin
      if (err == 0)
         $display("PASS! All data have been generated successfully!");
      else begin
      $display("---------------------------------------------");
         $display("There are %d errors!", err);
      $display("---------------------------------------------");
      end
      $display("---------------------------------------------");
      total_num = total_cycle_num * `CYCLE ;
      $display("Total delay: %d ns", total_num );
      $display("---------------------------------------------");
      $finish;
    end
end

always @ ( posedge clk) begin
   if (reset == 1'b1) 
      total_cycle_num = 0 ;
   else 
      total_cycle_num = total_cycle_num + 1 ;
end 

endmodule

pre-sim/dump.vcd
$date
	Mon Jan 13 20:48:38 2014
$end
$version
	ModelSim Version 10.1d
$end
$timescale
	10ps
$end
$scope module test $end
$var parameter 48 ! INPUT_DATA $end
$var parameter 80 " EXPECT_DATA $end
$var reg 1 # clk $end
$var reg 1 $ reset $end
$var reg 1 % nt $end
$var reg 8 & xi [7:0] $end
$var reg 8 ' yi [7:0] $end
$var wire 1 ( xo [7] $end
$var wire 1 ) xo [6] $end
$var wire 1 * xo [5] $end
$var wire 1 + xo [4] $end
$var wire 1 , xo [3] $end
$var wire 1 - xo [2] $end
$var wire 1 . xo [1] $end
$var wire 1 / xo [0] $end
$var wire 1 0 yo [7] $end
$var wire 1 1 yo [6] $end
$var wire 1 2 yo [5] $end
$var wire 1 3 yo [4] $end
$var wire 1 4 yo [3] $end
$var wire 1 5 yo [2] $end
$var wire 1 6 yo [1] $end
$var wire 1 7 yo [0] $end
$var wire 1 8 po $end
$var wire 1 9 busy $end
$var integer 32 : i $end
$var integer 32 ; j $end
$var integer 32 < k $end
$var integer 32 = l $end
$var integer 32 > m $end
$var integer 32 ? out_f $end
$var integer 32 @ err $end
$var integer 32 A pattern_num $end
$var integer 32 B total_num $end
$var integer 32 C total_cycle_num $end
$var integer 32 D a $end
$var integer 32 E b $end
$var integer 32 F c $end
$var integer 32 G d $end
$var reg 16 H data_tmp_expect [15:0] $end
$var reg 16 I data_tmp_i [15:0] $end
$var reg 16 J data_tmp_i1 [15:0] $end
$var reg 16 K data_tmp_i2 [15:0] $end
$var reg 16 L data_tmp_i3 [15:0] $end
$scope module top $end
$var parameter 32 M S0_RST $end
$var parameter 32 N S1_WAIT $end
$var parameter 32 O S2_START $end
$var parameter 32 P S3_RX_ENDPOINT $end
$var parameter 32 Q S4_PREPARE_CAL $end
$var parameter 32 R S5_CAL $end
$var parameter 32 S S6_TX_RESULT $end
$var wire 1 T clk $end
$var wire 1 U reset $end
$var wire 1 V nt $end
$var wire 1 W xi [7] $end
$var wire 1 X xi [6] $end
$var wire 1 Y xi [5] $end
$var wire 1 Z xi [4] $end
$var wire 1 [ xi [3] $end
$var wire 1 \ xi [2] $end
$var wire 1 ] xi [1] $end
$var wire 1 ^ xi [0] $end
$var wire 1 _ yi [7] $end
$var wire 1 ` yi [6] $end
$var wire 1 a yi [5] $end
$var wire 1 b yi [4] $end
$var wire 1 c yi [3] $end
$var wire 1 d yi [2] $end
$var wire 1 e yi [1] $end
$var wire 1 f yi [0] $end
$var wire 1 8 po $end
$var reg 1 g busy $end
$var wire 1 ( xo [7] $end
$var wire 1 ) xo [6] $end
$var wire 1 * xo [5] $end
$var wire 1 + xo [4] $end
$var wire 1 , xo [3] $end
$var wire 1 - xo [2] $end
$var wire 1 . xo [1] $end
$var wire 1 / xo [0] $end
$var wire 1 0 yo [7] $end
$var wire 1 1 yo [6] $end
$var wire 1 2 yo [5] $end
$var wire 1 3 yo [4] $end
$var wire 1 4 yo [3] $end
$var wire 1 5 yo [2] $end
$var wire 1 6 yo [1] $end
$var wire 1 7 yo [0] $end
$var reg 3 h curr_state [2:0] $end
$var reg 3 i next_state [2:0] $end
$var reg 1 j count_flag $end
$var reg 32 k end_point_x [31:0] $end
$var reg 32 l end_point_y [31:0] $end
$var reg 3 m cnt [2:0] $end
$var wire 1 n finish $end
$scope module t1 $end
$var parameter 32 o S0_RST $end
$var parameter 32 p S1_PAR_INIT $end
$var parameter 32 q S2_OUTER_LOOP $end
$var parameter 32 r S3_END_X_INIT $end
$var parameter 32 s S4_OUTPUT $end
$var parameter 32 t S5_INCRESE_SLOPE $end
$var parameter 32 u S6_FINISH $end
$var reg 1 v po $end
$var reg 1 w finish $end
$var reg 8 x xo [7:0] $end
$var reg 8 y yo [7:0] $end
$var wire 1 T clk $end
$var wire 1 z count_flag $end
$var wire 1 { point_x [31] $end
$var wire 1 | point_x [30] $end
$var wire 1 } point_x [29] $end
$var wire 1 ~ point_x [28] $end
$var wire 1 !! point_x [27] $end
$var wire 1 "! point_x [26] $end
$var wire 1 #! point_x [25] $end
$var wire 1 $! point_x [24] $end
$var wire 1 %! point_x [23] $end
$var wire 1 &! point_x [22] $end
$var wire 1 '! point_x [21] $end
$var wire 1 (! point_x [20] $end
$var wire 1 )! point_x [19] $end
$var wire 1 *! point_x [18] $end
$var wire 1 +! point_x [17] $end
$var wire 1 ,! point_x [16] $end
$var wire 1 -! point_x [15] $end
$var wire 1 .! point_x [14] $end
$var wire 1 /! point_x [13] $end
$var wire 1 0! point_x [12] $end
$var wire 1 1! point_x [11] $end
$var wire 1 2! point_x [10] $end
$var wire 1 3! point_x [9] $end
$var wire 1 4! point_x [8] $end
$var wire 1 5! point_x [7] $end
$var wire 1 6! point_x [6] $end
$var wire 1 7! point_x [5] $end
$var wire 1 8! point_x [4] $end
$var wire 1 9! point_x [3] $end
$var wire 1 :! point_x [2] $end
$var wire 1 ;! point_x [1] $end
$var wire 1 <! point_x [0] $end
$var wire 1 =! point_y [31] $end
$var wire 1 >! point_y [30] $end
$var wire 1 ?! point_y [29] $end
$var wire 1 @! point_y [28] $end
$var wire 1 A! point_y [27] $end
$var wire 1 B! point_y [26] $end
$var wire 1 C! point_y [25] $end
$var wire 1 D! point_y [24] $end
$var wire 1 E! point_y [23] $end
$var wire 1 F! point_y [22] $end
$var wire 1 G! point_y [21] $end
$var wire 1 H! point_y [20] $end
$var wire 1 I! point_y [19] $end
$var wire 1 J! point_y [18] $end
$var wire 1 K! point_y [17] $end
$var wire 1 L! point_y [16] $end
$var wire 1 M! point_y [15] $end
$var wire 1 N! point_y [14] $end
$var wire 1 O! point_y [13] $end
$var wire 1 P! point_y [12] $end
$var wire 1 Q! point_y [11] $end
$var wire 1 R! point_y [10] $end
$var wire 1 S! point_y [9] $end
$var wire 1 T! point_y [8] $end
$var wire 1 U! point_y [7] $end
$var wire 1 V! point_y [6] $end
$var wire 1 W! point_y [5] $end
$var wire 1 X! point_y [4] $end
$var wire 1 Y! point_y [3] $end
$var wire 1 Z! point_y [2] $end
$var wire 1 [! point_y [1] $end
$var wire 1 \! point_y [0] $end
$var reg 18 ]! dxl [17:0] $end
$var reg 18 ^! dxr [17:0] $end
$var reg 18 _! xl [17:0] $end
$var reg 18 `! xr [17:0] $end
$var reg 8 a! end_x [7:0] $end
$var reg 3 b! curr_state [2:0] $end
$var reg 3 c! next_state [2:0] $end
$var reg 8 d! i [7:0] $end
$var reg 8 e! j [7:0] $end
$var reg 1 f! init_slope $end
$var reg 1 g! init_end_x $end
$var reg 1 h! outdata $end
$var reg 1 i! plus_slope $end
$var reg 1 j! init_i $end
$var reg 18 k! tmp_x [17:0] $end
$var reg 18 l! tmp_y [17:0] $end
$upscope $end
$upscope $end
$upscope $end
$enddefinitions $end
#0
$dumpvars
1#
0$
0%
bz &
bz '
bx H
bx I
bx J
bx K
bx L
xg
bx h
bx i
xj
bx k
bx l
b0 m
0v
0w
bx x
bx y
bx ]!
bx ^!
bx _!
bx `!
bx a!
b0 b!
b1 c!
bx d!
bx e!
0f!
0g!
0h!
0i!
0j!
bx k!
bx l!
b0 M
b1 N
b10 O
b11 P
b100 Q
b101 R
b110 S
b0 o
b1 p
b10 q
b11 r
b100 s
b101 t
b110 u
b10010010100111000101110010001000100000101010100 !
b1000101010110000101000001000101010000110101010000101110010001000100000101010100 "
b0 :
b0 ;
b0 <
b0 =
bx >
b10 ?
b0 @
b1 A
b0 B
bx C
bx D
bx E
bx F
bx G
x;!
x:!
x9!
x8!
x7!
x6!
x5!
x4!
x3!
x2!
x1!
x0!
x/!
x.!
x-!
x,!
x+!
x*!
x)!
x(!
x'!
x&!
x%!
x$!
x#!
x"!
x!!
x~
x}
x|
x{
xz
x/
x.
x-
x,
x+
x*
x)
x(
x7
x6
x5
x4
x3
x2
x1
x0
08
x9
0n
zf
ze
zd
zc
zb
za
z`
z_
z^
z]
z\
z[
zZ
zY
zX
zW
0V
0U
1T
x\!
x[!
xZ!
xY!
xX!
xW!
xV!
xU!
xT!
xS!
xR!
xQ!
xP!
xO!
xN!
xM!
xL!
xK!
xJ!
xI!
xH!
xG!
xF!
xE!
xD!
xC!
xB!
xA!
x@!
x?!
x>!
x=!
x<!
$end
#5000
0#
0T
1$
1U
b0 h
b0 i
1g
0j
19
0z
#10000
1#
1T
b0 C
#14990
0$
0U
b1 i
#15000
0#
0T
#20000
1#
1T
b1 h
b1 C
b10 i
0g
09
#25000
0#
0T
b100 <
#30000
1#
1T
b10 h
b10 C
#35000
0#
0T
1%
1V
b11 i
#38000
b1000001100 I
b10 &
b1100 '
0f
0e
1d
1c
0b
0a
0`
0_
0^
1]
0\
0[
0Z
0Y
0X
0W
#40000
1#
1T
b11 h
b1 m
bx00000010 k
bx0000001000000000 k
bx00001100 l
bx0000110000000000 l
b11 C
0\!
0[!
0Z!
0Y!
0X!
0W!
0V!
0U!
0T!
0S!
1R!
1Q!
0P!
0O!
0N!
0M!
0<!
0;!
0:!
09!
08!
07!
06!
05!
04!
13!
02!
01!
00!
0/!
0.!
0-!
#42000
bz &
bz '
zf
ze
zd
zc
zb
za
z`
z_
z^
z]
z\
z[
zZ
zY
zX
zW
#45000
0#
0T
0%
0V
#48000
b100100001100 J
b1001 &
b1100 '
0f
0e
1d
1c
0b
0a
0`
0_
1^
0]
0\
1[
0Z
0Y
0X
0W
#50000
1#
1T
b10 m
bx0000001000001001 k
bx000000100000100100000000 k
bx0000110000001100 l
bx000011000000110000000000 l
b100 C
0L!
0K!
1J!
1I!
0H!
0G!
0F!
0E!
14!
03!
11!
0,!
1+!
0*!
0)!
0(!
0'!
0&!
0%!
#52000
bz &
bz '
zf
ze
zd
zc
zb
za
z`
z_
z^
z]
z\
z[
zZ
zY
zX
zW
#55000
0#
0T
#58000
b0 K
b0 &
b0 '
0f
0e
0d
0c
0b
0a
0`
0_
0^
0]
0\
0[
0Z
0Y
0X
0W
#60000
1#
1T
b11 m
b10000010010000000000000000 k
b1100000011000000000000000000 l
b101 C
0R!
0Q!
0D!
0C!
1B!
1A!
0@!
0?!
0>!
0=!
04!
01!
1,!
0+!
1)!
0$!
1#!
0"!
0!!
0~
0}
0|
0{
b100 i
#62000
bz &
bz '
zf
ze
zd
zc
zb
za
z`
z_
z^
z]
z\
z[
zZ
zY
zX
zW
#65000
0#
0T
#68000
b1000000000000 L
b10000 &
b0 '
0f
0e
0d
0c
0b
0a
0`
0_
0^
0]
0\
0[
1Z
0Y
0X
0W
#70000
1#
1T
b100 h
b10000010010000000000010000 k
b110 C
18!
b101 i
1g
19
#72000
bz &
bz '
b100 :
zf
ze
zd
zc
zb
za
z`
z_
z^
z]
z\
z[
zZ
zY
zX
zW
#75000
0#
0T
b0 <
#80000
1#
1T
b101 h
b0 m
b111 C
1j
1z
b1 b!
b10 c!
1f!
b100000000000 k!
b1100 l!
b10101010 ]!
b111110010000000000 k!
b111111110110101011 ^!
b0 _!
b100000000000000 `!
#85000
0#
0T
#90000
1#
1T
b10 b!
b1000 C
b11 c!
0f!
1j!
b0 d!
#95000
0#
0T
#100000
1#
1T
b11 b!
b1001 C
b100 c!
0j!
1g!
b10000 a!
b0 e!
#105000
0#
0T
#110000
1#
1T
b100 b!
b1010 C
0g!
1h!
#115000
0#
0T
#120000
1#
1T
1v
b0 x
b0 y
b1 e!
b1011 C
18
07
06
05
04
03
02
01
00
0/
0.
0-
0,
0+
0*
0)
0(
#125000
0#
0T
#130000
1#
1T
b1 x
b10 e!
b0 H
b1 =
b1100 C
1/
#135000
0#
0T
#140000
1#
1T
b10 x
b11 e!
b100000000 H
b10 =
b1101 C
0/
1.
#145000
0#
0T
#150000
1#
1T
b11 x
b100 e!
b1000000000 H
b11 =
b1110 C
1/
#155000
0#
0T
#160000
1#
1T
b100 x
b101 e!
b1100000000 H
b100 =
b1111 C
0/
0.
1-
#165000
0#
0T
#170000
1#
1T
b101 x
b110 e!
b10000000000 H
b101 =
b10000 C
1/
#175000
0#
0T
#180000
1#
1T
b110 x
b111 e!
b10100000000 H
b110 =
b10001 C
0/
1.
#185000
0#
0T
#190000
1#
1T
b111 x
b1000 e!
b11000000000 H
b111 =
b10010 C
1/
#195000
0#
0T
#200000
1#
1T
b1000 x
b1001 e!
b11100000000 H
b1000 =
b10011 C
0/
0.
0-
1,
#205000
0#
0T
#210000
1#
1T
b1001 x
b1010 e!
b100000000000 H
b1001 =
b10100 C
1/
#215000
0#
0T
#220000
1#
1T
b1010 x
b1011 e!
b100100000000 H
b1010 =
b10101 C
0/
1.
#225000
0#
0T
#230000
1#
1T
b1011 x
b1100 e!
b101000000000 H
b1011 =
b10110 C
1/
#235000
0#
0T
#240000
1#
1T
b1100 x
b1101 e!
b101100000000 H
b1100 =
b10111 C
0/
0.
1-
#245000
0#
0T
#250000
1#
1T
b1101 x
b1110 e!
b110000000000 H
b1101 =
b11000 C
1/
#255000
0#
0T
#260000
1#
1T
b1110 x
b1111 e!
b110100000000 H
b1110 =
b11001 C
0/
1.
#265000
0#
0T
#270000
1#
1T
b1111 x
b10000 e!
b111000000000 H
b1111 =
b11010 C
1/
b101 c!
#275000
0#
0T
#280000
1#
1T
b101 b!
b10000 x
b10001 e!
b111100000000 H
b10000 =
b11011 C
0/
0.
0-
0,
1+
b11 c!
0h!
1i!
b10101010 _!
b11110110101011 `!
b1 d!
#285000
0#
0T
#290000
1#
1T
b11 b!
0v
b1000000000000 H
b10001 =
b11100 C
08
b100 c!
0i!
1g!
b1111 a!
b0 e!
#295000
0#
0T
#300000
1#
1T
b100 b!
b11101 C
0g!
1h!
#305000
0#
0T
#310000
1#
1T
1v
b0 x
b1 y
b1 e!
b11110 C
18
17
0+
#315000
0#
0T
#320000
1#
1T
b1 x
b10 e!
b1 H
b10010 =
b11111 C
1/
#325000
0#
0T
#330000
1#
1T
b10 x
b11 e!
b100000001 H
b10011 =
b100000 C
0/
1.
#335000
0#
0T
#340000
1#
1T
b11 x
b100 e!
b1000000001 H
b10100 =
b100001 C
1/
#345000
0#
0T
#350000
1#
1T
b100 x
b101 e!
b1100000001 H
b10101 =
b100010 C
0/
0.
1-
#355000
0#
0T
#360000
1#
1T
b101 x
b110 e!
b10000000001 H
b10110 =
b100011 C
1/
#365000
0#
0T
#370000
1#
1T
b110 x
b111 e!
b10100000001 H
b10111 =
b100100 C
0/
1.
#375000
0#
0T
#380000
1#
1T
b111 x
b1000 e!
b11000000001 H
b11000 =
b100101 C
1/
#385000
0#
0T
#390000
1#
1T
b1000 x
b1001 e!
b11100000001 H
b11001 =
b100110 C
0/
0.
0-
1,
#395000
0#
0T
#400000
1#
1T
b1001 x
b1010 e!
b100000000001 H
b11010 =
b100111 C
1/
#405000
0#
0T
#410000
1#
1T
b1010 x
b1011 e!
b100100000001 H
b11011 =
b101000 C
0/
1.
#415000
0#
0T
#420000
1#
1T
b1011 x
b1100 e!
b101000000001 H
b11100 =
b101001 C
1/
#425000
0#
0T
#430000
1#
1T
b1100 x
b1101 e!
b101100000001 H
b11101 =
b101010 C
0/
0.
1-
#435000
0#
0T
#440000
1#
1T
b1101 x
b1110 e!
b110000000001 H
b11110 =
b101011 C
1/
#445000
0#
0T
#450000
1#
1T
b1110 x
b1111 e!
b110100000001 H
b11111 =
b101100 C
0/
1.
b101 c!
#455000
0#
0T
#460000
1#
1T
b101 b!
b1111 x
b10000 e!
b111000000001 H
b100000 =
b101101 C
1/
b11 c!
0h!
1i!
b101010100 _!
b11101101010110 `!
b10 d!
#465000
0#
0T
#470000
1#
1T
b11 b!
0v
b111100000001 H
b100001 =
b101110 C
08
b100 c!
0i!
1g!
b1110 a!
b0 e!
#475000
0#
0T
#480000
1#
1T
b100 b!
b101111 C
0g!
1h!
#485000
0#
0T
#490000
1#
1T
1v
b0 x
b10 y
b1 e!
b110000 C
18
07
16
0/
0.
0-
0,
#495000
0#
0T
#500000
1#
1T
b1 x
b10 e!
b10 H
b100010 =
b110001 C
1/
#505000
0#
0T
#510000
1#
1T
b10 x
b11 e!
b100000010 H
b100011 =
b110010 C
0/
1.
#515000
0#
0T
#520000
1#
1T
b11 x
b100 e!
b1000000010 H
b100100 =
b110011 C
1/
#525000
0#
0T
#530000
1#
1T
b100 x
b101 e!
b1100000010 H
b100101 =
b110100 C
0/
0.
1-
#535000
0#
0T
#540000
1#
1T
b101 x
b110 e!
b10000000010 H
b100110 =
b110101 C
1/
#545000
0#
0T
#550000
1#
1T
b110 x
b111 e!
b10100000010 H
b100111 =
b110110 C
0/
1.
#555000
0#
0T
#560000
1#
1T
b111 x
b1000 e!
b11000000010 H
b101000 =
b110111 C
1/
#565000
0#
0T
#570000
1#
1T
b1000 x
b1001 e!
b11100000010 H
b101001 =
b111000 C
0/
0.
0-
1,
#575000
0#
0T
#580000
1#
1T
b1001 x
b1010 e!
b100000000010 H
b101010 =
b111001 C
1/
#585000
0#
0T
#590000
1#
1T
b1010 x
b1011 e!
b100100000010 H
b101011 =
b111010 C
0/
1.
#595000
0#
0T
#600000
1#
1T
b1011 x
b1100 e!
b101000000010 H
b101100 =
b111011 C
1/
#605000
0#
0T
#610000
1#
1T
b1100 x
b1101 e!
b101100000010 H
b101101 =
b111100 C
0/
0.
1-
#615000
0#
0T
#620000
1#
1T
b1101 x
b1110 e!
b110000000010 H
b101110 =
b111101 C
1/
b101 c!
#625000
0#
0T
#630000
1#
1T
b101 b!
b1110 x
b1111 e!
b110100000010 H
b101111 =
b111110 C
0/
1.
b11 c!
0h!
1i!
b111111110 _!
b11100100000001 `!
b11 d!
#635000
0#
0T
#640000
1#
1T
b11 b!
0v
b111000000010 H
b110000 =
b111111 C
08
b100 c!
0i!
1g!
b0 e!
#645000
0#
0T
#650000
1#
1T
b100 b!
b1000000 C
0g!
1h!
#655000
0#
0T
#660000
1#
1T
1v
b0 x
b11 y
b1 e!
b1000001 C
18
17
0.
0-
0,
#665000
0#
0T
#670000
1#
1T
b1 x
b10 e!
b11 H
b110001 =
b1000010 C
1/
#675000
0#
0T
#680000
1#
1T
b10 x
b11 e!
b100000011 H
b110010 =
b1000011 C
0/
1.
#685000
0#
0T
#690000
1#
1T
b11 x
b100 e!
b1000000011 H
b110011 =
b1000100 C
1/
#695000
0#
0T
#700000
1#
1T
b100 x
b101 e!
b1100000011 H
b110100 =
b1000101 C
0/
0.
1-
#705000
0#
0T
#710000
1#
1T
b101 x
b110 e!
b10000000011 H
b110101 =
b1000110 C
1/
#715000
0#
0T
#720000
1#
1T
b110 x
b111 e!
b10100000011 H
b110110 =
b1000111 C
0/
1.
#725000
0#
0T
